beaker/__init__.py
beaker/application.py
beaker/build_options.py
beaker/client/__init__.py
beaker/client/api_providers.py
beaker/client/application_client.py
beaker/compilation.py
beaker/consts.py
beaker/decorators.py
beaker/lib/__init__.py
beaker/lib/inline.py
beaker/lib/iter.py
beaker/lib/math.py
beaker/lib/storage/__init__.py
beaker/lib/storage/blob.py
beaker/lib/storage/box_list.py
beaker/lib/storage/box_mapping.py
beaker/lib/storage/global_blob.py
beaker/lib/storage/local_blob.py
beaker/lib/strings.py
beaker/localnet/__init__.py
beaker/localnet/clients.py
beaker/localnet/kmd.py
beaker/logic_signature.py
beaker/precompile.py
beaker/py.typed
beaker/sandbox/__init__.py
beaker/sandbox/clients.py
beaker/sandbox/kmd.py
beaker/state/__init__.py
beaker/state/_abc.py
beaker/state/_aggregate.py
beaker/state/blob.py
beaker/state/primitive.py
beaker/state/reserved.py
beaker_pyteal-1.0.1.dist-info/LICENSE
beaker_pyteal-1.0.1.dist-info/METADATA
beaker_pyteal-1.0.1.dist-info/WHEEL
beaker_pyteal-1.0.1.dist-info/RECORD
