Metadata-Version: 2.1
Name: beaker-pyteal
Version: 1.0.1
Summary: A Framework for building PyTeal Applications
Home-page: https://beaker.algo.xyz
License: MIT
Keywords: pyteal,algorand
Author: Ben Guidarelli
Author-email: ben@algorand.com
Requires-Python: >=3.10,<4.0
Classifier: Development Status :: 2 - Pre-Alpha
Classifier: License :: OSI Approved :: MIT License
Classifier: Programming Language :: Python :: 3
Classifier: Programming Language :: Python :: 3.10
Classifier: Programming Language :: Python :: 3.11
Requires-Dist: algokit-utils (>=1.0.2,<2.0.0)
Requires-Dist: py-algorand-sdk (>=2.0.0)
Requires-Dist: pyteal (>=0.24,<0.25)
Project-URL: Repository, https://github.com/algorand-devrel/beaker
